poe.py
poe_graphql/AddHumanMessageMutation.graphql
poe_graphql/AddMessageBreakMutation.graphql
poe_graphql/AutoSubscriptionMutation.graphql
poe_graphql/BioFragment.graphql
poe_graphql/ChatAddedSubscription.graphql
poe_graphql/ChatFragment.graphql
poe_graphql/ChatListPaginationQuery.graphql
poe_graphql/ChatPaginationQuery.graphql
poe_graphql/ChatViewQuery.graphql
poe_graphql/DeleteHumanMessagesMutation.graphql
poe_graphql/DeleteMessageMutation.graphql
poe_graphql/HandleFragment.graphql
poe_graphql/LoginWithVerificationCodeMutation.graphql
poe_graphql/MessageAddedSubscription.graphql
poe_graphql/MessageDeletedSubscription.graphql
poe_graphql/MessageFragment.graphql
poe_graphql/MessageRemoveVoteMutation.graphql
poe_graphql/MessageSetVoteMutation.graphql
poe_graphql/SendMessageMutation.graphql
poe_graphql/SendVerificationCodeForLoginMutation.graphql
poe_graphql/ShareMessagesMutation.graphql
poe_graphql/SignupWithVerificationCodeMutation.graphql
poe_graphql/StaleChatUpdateMutation.graphql
poe_graphql/SubscriptionsMutation.graphql
poe_graphql/SummarizePlainPostQuery.graphql
poe_graphql/SummarizeQuotePostQuery.graphql
poe_graphql/SummarizeSharePostQuery.graphql
poe_graphql/UserSnippetFragment.graphql
poe_graphql/ViewerInfoQuery.graphql
poe_graphql/ViewerStateFragment.graphql
poe_graphql/ViewerStateUpdatedSubscription.graphql
poe_graphql/__init__.py
poe_web_client-0.0.7.dist-info/LICENSE
poe_web_client-0.0.7.dist-info/METADATA
poe_web_client-0.0.7.dist-info/WHEEL
poe_web_client-0.0.7.dist-info/top_level.txt
poe_web_client-0.0.7.dist-info/RECORD
