Metadata-Version: 2.1
Name: poe-web-client
Version: 0.0.7
Summary: A reverse engineered API wrapper for Quora's Poe,fork from https://github.com/ading2210/poe-api
Home-page: https://github.com/libaiabcd/poe-api
Author: libaiabcd
License: GPLv3
Classifier: Programming Language :: Python :: 3
Classifier: License :: OSI Approved :: GNU General Public License (GPL)
Classifier: Operating System :: OS Independent
Requires-Python: >=3.7
License-File: LICENSE
Requires-Dist: websocket-client
Requires-Dist: requests[socks]
Requires-Dist: python-socks
